osensaimos/__init__.py
osensaimos/anglestest.py
osensaimos/minimalmodbusosensa.py
osensaimos/osensaimos.py
osensaimos/osensaplot.py
osensaplantiga/__init__.py
osensaplantiga/minimalmodbusosensa.py
osensaplantiga/osensaplantiga.py
osensaplantiga/test_osensaplantiga.py
osensaplantiga-0.1.8.dist-info/METADATA
osensaplantiga-0.1.8.dist-info/RECORD
osensaplantiga-0.1.8.dist-info/WHEEL
osensaplantiga-0.1.8.dist-info/top_level.txt
