Metadata-Version: 2.1
Name: osensaplantiga
Version: 0.1.8
Summary: OSENSA-Plantiga Python library
Home-page: UNKNOWN
Author: OSENSA Innovations
Author-email: cng@osensa.com
License: MIT
Requires-Dist: pyserial
Requires-Dist: python-dateutil
Requires-Dist: xmodem
